taskscore2/__init__.py
taskscore2/prioritizer.py
taskscore2-0.1.2.dist-info/LICENSE
taskscore2-0.1.2.dist-info/METADATA
taskscore2-0.1.2.dist-info/WHEEL
taskscore2-0.1.2.dist-info/RECORD
