Metadata-Version: 2.1
Name: taskscore2
Version: 0.1.2
Summary: 
Author: Paulo Mulotto
Author-email: you@example.com
Requires-Python: >=3.11,<4.0
Classifier: Programming Language :: Python :: 3
Classifier: Programming Language :: Python :: 3.11
Classifier: Programming Language :: Python :: 3.12
